ivolat/ivolat.pyd
ivolat/ivolat.so
ivolat/__init__.py
ivolat-0.1.2.dist-info/DESCRIPTION.rst
ivolat-0.1.2.dist-info/METADATA
ivolat-0.1.2.dist-info/metadata.json
ivolat-0.1.2.dist-info/RECORD
ivolat-0.1.2.dist-info/top_level.txt
ivolat-0.1.2.dist-info/WHEEL
